starbound_dungeons/__init__.py
starbound_dungeons/indexer.py
py_starbound_dungeons-0.1.0.dist-info/LICENSE
py_starbound_dungeons-0.1.0.dist-info/METADATA
py_starbound_dungeons-0.1.0.dist-info/WHEEL
py_starbound_dungeons-0.1.0.dist-info/entry_points.txt
py_starbound_dungeons-0.1.0.dist-info/top_level.txt
py_starbound_dungeons-0.1.0.dist-info/RECORD
