Metadata-Version: 2.1
Name: py-starbound-dungeons
Version: 0.1.0
Summary: Utility for indexing Starbound dungeon files
Author: rl.starbound
Project-URL: Homepage, https://github.com/rl-starbound/py-starbound-dungeons
Project-URL: Bug Tracker, https://github.com/rl-starbound/py-starbound-dungeons/issues
Classifier: Programming Language :: Python :: 3
Classifier: License :: OSI Approved :: MIT License
Classifier: Operating System :: OS Independent
Requires-Python: >=3.7
License-File: LICENSE
Requires-Dist: JSON-minify (>=0.3.0)
Requires-Dist: Pillow (>=9.4.0)
Requires-Dist: pytiled-parser (>=2.2.1)
